alphavantage/__init__.py
alphavantage/_version.py
alphavantage/dates.py
alphavantage/price_history.py
alphavantage/reference.py
alphavantage/symbology.py
alphavantage/web.py
alphavantage-0.0.11.dist-info/LICENSE.txt
alphavantage-0.0.11.dist-info/METADATA
alphavantage-0.0.11.dist-info/RECORD
alphavantage-0.0.11.dist-info/WHEEL
alphavantage-0.0.11.dist-info/top_level.txt
