Metadata-Version: 2.1
Name: alphavantage
Version: 0.0.11
Summary: Alphavantage API wrapper.
Home-page: https://github.com/portfoliome/alphavantage
Author: Philip Martin
Author-email: philip.martin@censible.co
License: MIT
Platform: UNKNOWN
Classifier: Development Status :: 3 - Alpha
Classifier: Intended Audience :: Financial and Insurance Industry
Classifier: Topic :: Office/Business :: Financial :: Investment
Classifier: Natural Language :: English
Classifier: Programming Language :: Python :: 3.6
Provides-Extra: test
